paragami/__init__.py
paragami/_version.py
paragami/autograd_supplement_lib.py
paragami/base_patterns.py
paragami/function_patterns.py
paragami/numeric_array_patterns.py
paragami/optimization_lib.py
paragami/pattern_containers.py
paragami/psdmatrix_patterns.py
paragami/sensitivity_lib.py
paragami/simplex_patterns.py
paragami/sparse_preconditioners_lib.py
paragami-0.42.dist-info/AUTHORS.rst
paragami-0.42.dist-info/LICENSE
paragami-0.42.dist-info/METADATA
paragami-0.42.dist-info/WHEEL
paragami-0.42.dist-info/entry_points.txt
paragami-0.42.dist-info/top_level.txt
paragami-0.42.dist-info/RECORD
