Metadata-Version: 1.1
Name: paragami
Version: 0.42
Summary: Python pacakge to flatten and fold parameter data structures.
Home-page: https://github.com/rgiordan/paragami
Author: Ryan Giordano
Author-email: rgiordan@gmail.com
License: UNKNOWN
Platform: UNKNOWN
Classifier: Programming Language :: Python :: 3
Classifier: Natural Language :: English
Classifier: License :: OSI Approved :: Apache Software License
Classifier: Intended Audience :: Science/Research
Classifier: Intended Audience :: Developers
Classifier: Development Status :: 2 - Pre-Alpha
Classifier: Topic :: Scientific/Engineering :: Mathematics
